[
{
"SNo": "1",
"Name": "Aakash Capital Limited",
"HO": "Thapathali, Kathamandu",
"phone": "015111145",
"email": "info@aakashcapital.com.np",
"website": "www.aakashcapital.com.np/",
"logo":"",
"ODAD":"",
"ODBS":"",
"license": "41",
"Capital": ""
},
{
"SNo": "2",
"Name": "Arks Capital Advisors Limited",
"HO": "Central Business Park, Thapathali , Kathmandu",
"phone": "015911676",
"email": "info@arkscapitaladvisors.com.np",
"website": "www.arkscapitalsdvisors.com/",
"logo":"",
"ODAD":"",
"ODBS":"",
"license": "43",
"Capital": ""
},
{
"SNo": "3",
"Name": "Asian Capital Limited",
"HO": "Maitidevi complex, Maitidevi, Kathmandu-32",
"phone": "014418664",
"phone1": "014416504",
"email": "info@asiancapital.com.np",
"website": "www.wealth.com.np/",
"logo":"",
"ODAD":"",
"ODBS":"",
"license": "42",
"Capital": ""
},
{
"SNo": "4",
"Name": "Citizen Investment Trus",
"HO": "New Baneshwor, Kathmandu",
"phone": "014785319",
"phone1": "014785321",
"email": "cit_cmkt@nlk.org.np",
"website": "www.nlk.org.np/",
"logo":"",
"ODAD":"",
"ODBS":"",
"license": "08",
"Capital": ""
},
{
"SNo": "5",
"Name": "Citizens Capital Limited",
"HO": "Batule Ghar, Dillibazar 33, Kathmandu, Bagmati, Nepal",
"phone": "014417723",
"phone1": "014417457",
"email": "info@citizenscapital.com.np",
"website": "www.citizenscapital.com.np/",
"logo":"",
"ODAD":"",
"ODBS":"",
"license": "34",
"Capital": ""
},
{
"SNo": "6",
"Name": "Elite Merchant Capital Limited",
"HO": "2nd Floor, Metro Park Building, Lazimpat-2, Kathmandu, Nepal",
"phone": "014425190",
"phone1": "",
"email": "elitecapitalnepal@gmail.com",
"website": "www.elitecapital.com.np/",
"logo":"",
"ODAD":"",
"ODBS":"",
"license": "54",
"Capital": ""
},
{
"SNo": "7",
"Name": "Garima Capital Limited",
"HO": "",
"phone": "",
"email": "",
"website": "","logo":"",
"ODAD":"",
"ODBS":"",
"license": "",
"Capital": ""
},
{
"SNo": "8",
"Name": "Global IME Capital Limited",
"HO": "",
"phone": "",
"email": "",
"website": "","logo":"",
"ODAD":"",
"ODBS":"",
"license": "",
"Capital": ""
},
{
"SNo": "9",
"Name": "Himalaya Securities Banker Limited",
"HO": "",
"phone": "",
"email": "",
"website": "","logo":"",
"Capital": "",
"ODAD":"",
"license": "",
"ODBS":""
},
{
"SNo": "10",
"Name": "Himalayan Capital Limited",
"HO": "",
"phone": "",
"email": "",
"website": "","logo":"",
"ODAD":"",
"ODBS":"",
"license": "",
"Capital": ""
},
{
"SNo": "11",
"Name": "Himalayan Investment Banker",
"HO": "",
"phone": "",
"email": "",
"website": "","logo":"",
"ODAD":"",
"ODBS":"",
"license": "",
"Capital": ""
},
{
"SNo": "12",
"Name": "Jyoti Capital Limited",
"HO": "",
"phone": "",
"email": "",
"website": "","logo":"",
"ODAD":"",
"ODBS":"",
"license": "",
"Capital": ""
},
{
"SNo": "13",
"Name": "Kumari Capital Limited",
"HO": "",
"phone": "",
"email": "",
"website": "","logo":"",
"ODAD":"",
"ODBS":"",
"license": "",
"Capital": ""
},
{
"SNo": "14",
"Name": "Laxmi Sunrise Capital Limited",
"HO": "",
"phone": "",
"email": "",
"website": "","logo":"",
"ODAD":"",
"ODBS":"",
"license": "",
"Capital": ""
},
{
"SNo": "15",
"Name": "Machhapuchhre Kriti Capital Limited",
"HO": "",
"phone": "",
"email": "",
"website": "","logo":"",
"ODAD":"",
"ODBS":"",
"license": "",
"Capital": ""
},
{
"SNo": "16",
"Name": "Market Pundit Capital & Merchant Banking Limited",
"HO": "",
"phone": "",
"email": "",
"website": "","logo":"",
"ODAD":"",
"ODBS":"",
"license": "",
"Capital": ""
},
{
"SNo": "17",
"Name": "Muktinath Capital Limited",
"HO": "",
"phone": "",
"email": "",
"website": "","logo":"",
"ODAD":"",
"ODBS":"",
"Capital": ""
},
{
"SNo": "18",
"Name": "Nabil Investment Bank Limited",
"HO": "",
"phone": "",
"email": "",
"website": "","logo":"",
"ODAD":"",
"ODBS":"",
"Capital": ""
},
{
"SNo": "19",
"Name": "Nepal Life Capital Limited",
"HO": "",
"phone": "",
"email": "",
"website": "","logo":"",
"ODAD":"",
"ODBS":"",
"Capital": ""
},
{
"SNo": "20",
"Name": "Nepal SBI Merchant Banking Limited",
"HO": "",
"phone": "",
"email": "",
"website": "","logo":"",
"ODAD":"",
"ODBS":"",
"Capital": ""
},
{
"SNo": "21",
"Name": "NIC Asia Capital Limited",
"HO": "",
"phone": "",
"email": "",
"website": "","logo":"",
"ODAD":"",
"ODBS":"",
"Capital": ""
},
{
"SNo": "22",
"Name": "NIMB ACE Capital Limited",
"HO": "",
"phone": "",
"email": "",
"website": "","logo":"",
"ODAD":"",
"ODBS":"",
"Capital": ""
},
{
"SNo": "23",
"Name": "NMB Capital Limited",
"HO": "",
"phone": "",
"email": "",
"website": "","logo":"",
"ODAD":"",
"ODBS":"",
"Capital": ""
},
{
"SNo": "24",
"Name": "Prabhu Capital Limited",
"HO": "",
"phone": "",
"email": "",
"website": "","logo":"",
"ODAD":"",
"ODBS":"",
"Capital": ""
},
{
"SNo": "25",
"Name": "Provident Merchant Banking Limited",
"HO": "",
"phone": "",
"email": "",
"website": "","logo":"",
"ODAD":"",
"ODBS":"",
"Capital": ""
},
{
"SNo": "26",
"Name": "RBB Merchant Banking Limited ",
"HO": "",
"phone": "",
"email": "",
"website": "","logo":"",
"ODAD":"",
"ODBS":"",
"Capital": ""
},
{
"SNo": "27",
"Name": "Reliable Investment & Merchant Capital Limited",
"HO": "",
"phone": "",
"email": "",
"website": "","logo":"",
"ODAD":"",
"ODBS":"",
"Capital": ""
},
{
"SNo": "28",
"Name": "Sampanna Capital and Advisory Nepal Limited",
"HO": "",
"phone": "",
"email": "",
"website": "","logo":"",
"ODAD":"",
"ODBS":"",
"Capital": ""
},
{
"SNo": "29",
"Name": "Sanima Capital Limited",
"HO": "",
"phone": "",
"email": "",
"website": "","logo":"",
"ODAD":"",
"ODBS":"",
"Capital": ""
},
{
"SNo": "30",
"Name": "Siddhartha Capital Limited",
"HO": "",
"phone": "",
"email": "",
"website": "","logo":"",
"ODAD":"",
"ODBS":"",
"Capital": ""
},
{
"SNo": "31",
"Name": "Sunlife Capital Limited",
"HO": "",
"phone": "",
"email": "",
"website": "","logo":"",
"ODAD":"",
"ODBS":"",
"Capital": ""
}




]
