[
  {
    "name": "Ujyaalo Radio Network",
    "frequency": "90.0 MHz",
    "logo": "https://example.com/logos/ujyaalo.png",
    "stream": "http://stream.zenolive.com/wtuvp08xq1duv"
  },
  {
    "name": "Hits FM",
    "frequency": "91.2 Mhz",
    "logo": "",
    "stream": "https://usa15.fastcast4u.com/proxy/hitsfm912?mp=/1"
  },
  {
    "name": "",
    "frequency": "",
    "logo": "",
    "stream": ""
  },
  {
    "name": "",
    "frequency": "",
    "logo": "",
    "stream": ""
  },
  {
    "name": "",
    "frequency": "",
    "logo": "",
    "stream": ""
  },
  {
    "name": "",
    "frequency": "",
    "logo": "",
    "stream": ""
  },
  {
    "name": "",
    "frequency": "",
    "logo": "",
    "stream": ""
  },
  {
    "name": "Radio Kantipur",
    "frequency": "96.1 MHz",
    "logo": "https://example.com/logos/kantipur.png",
    "stream": "https://radio-broadcast.ekantipur.com/stream"
  },
  {
    "name": "Classic FM",
    "frequency": "101.2 Mhz",
    "logo": "",
    "stream": "https://radio-streaming-serv-1.hamropatro.com/radio/8060/radio.mp3"
  },
  {
    "name": "Radio Janasanchar",
    "frequency": "107.9 Mhz",
    "logo": "https://example.com/logos/kalika.png",
    "stream": "https://online.net.np/8116/stream"
  }
]
