{
    "dipayal": [
        {
            "petrol": "",
            "diesel": "",
            "kerossene": "",
            "aviation": "",
            "aviationjet": "",
            "gas": ""
        }
    ],
    "Pokhara": [
        {
            "petrol": "",
            "diesel": "",
            "kerossene": "",
            "aviation": "",
            "aviationjet": "",
            "gas": ""
        }
    ],
    "surkhet": [
        {
            "petrol": "",
            "diesel": "",
            "kerossene": "",
            "aviation": "",
            "aviationjet": "",
            "gas": ""
        }
    ],
    "kathmandu": [
        {
            "petrol": "",
            "diesel": "",
            "kerossene": "",
            "aviation": "",
            "aviationjet": "",
            "gas": ""
        }
    ],
    "charali": [
        {
            "petrol": "",
            "diesel": "",
            "kerossene": "",
            "aviation": "",
            "aviationjet": "",
            "gas": ""
        }
    ]
}
